Workbook

Sheet Resumen
A2: CONSOLIDADO GERENCIAL
A3: 2026-10-01 al 2026-10-16 · Todos los usuarios y almacenes · Soles
A5: Línea de negocio | B5: Servicios | C5: Mercadería | D5: Sin clasificar | E5: TOTAL EMPRESA
A6: Venta neta | B6: =SUM('Diario'!B2:B17) -> 0 | C6: =SUM('Diario'!C2:C17) -> 28732.75 | D6: =SUM('Diario'!D2:D17) -> 0 | E6: =SUM('Diario'!E2:E17) -> 28732.75
A7: Costo vendido | B7: =SUM('Diario'!F2:F17) -> 0 | C7: =SUM('Diario'!G2:G17) -> 21240.6 | D7: =SUM('Diario'!H2:H17) -> 0 | E7: =SUM('Diario'!I2:I17) -> 21240.6
A8: UTILIDAD BRUTA | B8: =SUM('Diario'!J2:J17) -> 0 | C8: =SUM('Diario'!K2:K17) -> 7492.15 | D8: =D6-D7 -> 0 | E8: =SUM('Diario'!L2:L17) -> 7492.15
A9: Margen bruto | B9: =IF(B6=0,"n.a.",B8/B6) -> n.a. | C9: =IF(C6=0,"n.a.",C8/C6) -> 0.26075297 | D9: =IF(D6=0,"n.a.",D8/D6) -> n.a. | E9: =IF(E6=0,"n.a.",E8/E6) -> 0.26075297
A12: Resultado operativo | B12: Importe (S/)
A13: Utilidad bruta total | B13: =SUM('Diario'!L2:L17) -> 7492.15
A14: Gastos operativos | B14: =SUM('Diario'!M2:M17) -> 20
A15: Pagos de personal | B15: =SUM('Diario'!N2:N17) -> 800
A16: UTILIDAD NETA OPERATIVA ESTIMADA | B16: =SUM('Diario'!O2:O17) -> 6672.15
A19: Salidas reales de dinero | B19: Importe (S/) | D19: Control de caja y bancos | E19: Importe (S/)
A20: Pagos a proveedores | B20: =SUM('Diario'!P2:P17) -> 5900 | D20: Cobros Yape / Plin | E20: =SUM('Diario'!T2:T17) -> 0
A21: Gastos operativos | B21: =SUM('Diario'!M2:M17) -> 20 | D21: Traslados internos | E21: =SUM('Diario'!S2:S17) -> 0
A22: Pagos de personal | B22: =SUM('Diario'!N2:N17) -> 800 | D22: Ingresos registrados | E22: =SUM('Diario'!W2:W17) -> 20
A23: Otras salidas no operativas | B23: =SUM('Diario'!Q2:Q17) -> 0
A24: Salidas por clasificar | B24: =SUM('Diario'!R2:R17) -> 0 | D24: Yape no es gasto ni salida.
A25: TOTAL SALIDAS EXTERNAS | B25: =SUM('Diario'!V2:V17) -> 6720 | D25: No duplica las ventas.
A28: Proyección por promedio histórico | B28: Valor
A29: Días calendario del período | B29: 16 | D29: Base: promedio del período.
A30: Utilidad neta promedio por día | B30: =B16/B29 -> 417.00937 | D30: Incluye días sin actividad.
A31: Días a proyectar (editable) | B31: 30 | D31: No es un saldo bancario.
A32: UTILIDAD NETA PROYECTADA | B32: =B30*B31 -> 12510.281
A35: Utilidad neta estimada según costos, gastos y personal registrados. Ver criterios y cobertura.
A36: Pagos de compras a proveedores se muestran como salidas sin duplicar el costo vendido.

Sheet Diario
A1: Fecha | B1: Venta servicios | C1: Venta mercadería | D1: Venta sin clasificar | E1: Venta total | F1: Costo servicios | G1: Costo mercadería | H1: Costo sin clasificar | I1: Costo total | J1: U. bruta servicios | K1: U. bruta mercadería | L1: U. bruta total | M1: Gastos operativos | N1: Pagos de personal | O1: U. neta operativa estimada | P1: Pagos a proveedores | Q1: Otras salidas no operativas | R1: Salidas por clasificar | S1: Traslados internos | T1: Cobros Yape / Plin | U1: Salidas registradas | V1: Salidas externas | W1: Ingresos caja registrados | X1: U. neta acumulada
A2: 46296 | B2: 0 | C2: 0 | D2: 0 | E2: =SUM(B2:D2) -> 0 | F2: 0 | G2: 0 | H2: 0 | I2: =SUM(F2:H2) -> 0 | J2: =B2-F2 -> 0 | K2: =C2-G2 -> 0 | L2: =E2-I2 -> 0 | M2: 0 | N2: 0 | O2: =L2-M2-N2 -> 0 | P2: 0 | Q2: 0 | R2: 0 | S2: 0 | T2: 0 | U2: =SUM(M2:N2,P2:S2) -> 0 | V2: =U2-S2 -> 0 | W2: 0 | X2: =O2 -> 0
A3: 46297 | B3: 0 | C3: 0 | D3: 0 | E3: =SUM(B3:D3) -> 0 | F3: 0 | G3: 0 | H3: 0 | I3: =SUM(F3:H3) -> 0 | J3: =B3-F3 -> 0 | K3: =C3-G3 -> 0 | L3: =E3-I3 -> 0 | M3: 0 | N3: 0 | O3: =L3-M3-N3 -> 0 | P3: 0 | Q3: 0 | R3: 0 | S3: 0 | T3: 0 | U3: =SUM(M3:N3,P3:S3) -> 0 | V3: =U3-S3 -> 0 | W3: 0 | X3: =X2+O3 -> 0
A4: 46298 | B4: 0 | C4: 0 | D4: 0 | E4: =SUM(B4:D4) -> 0 | F4: 0 | G4: 0 | H4: 0 | I4: =SUM(F4:H4) -> 0 | J4: =B4-F4 -> 0 | K4: =C4-G4 -> 0 | L4: =E4-I4 -> 0 | M4: 0 | N4: 0 | O4: =L4-M4-N4 -> 0 | P4: 0 | Q4: 0 | R4: 0 | S4: 0 | T4: 0 | U4: =SUM(M4:N4,P4:S4) -> 0 | V4: =U4-S4 -> 0 | W4: 0 | X4: =X3+O4 -> 0
A5: 46299 | B5: 0 | C5: 0 | D5: 0 | E5: =SUM(B5:D5) -> 0 | F5: 0 | G5: 0 | H5: 0 | I5: =SUM(F5:H5) -> 0 | J5: =B5-F5 -> 0 | K5: =C5-G5 -> 0 | L5: =E5-I5 -> 0 | M5: 0 | N5: 0 | O5: =L5-M5-N5 -> 0 | P5: 0 | Q5: 0 | R5: 0 | S5: 0 | T5: 0 | U5: =SUM(M5:N5,P5:S5) -> 0 | V5: =U5-S5 -> 0 | W5: 0 | X5: =X4+O5 -> 0
A6: 46300 | B6: 0 | C6: 0 | D6: 0 | E6: =SUM(B6:D6) -> 0 | F6: 0 | G6: 0 | H6: 0 | I6: =SUM(F6:H6) -> 0 | J6: =B6-F6 -> 0 | K6: =C6-G6 -> 0 | L6: =E6-I6 -> 0 | M6: 0 | N6: 0 | O6: =L6-M6-N6 -> 0 | P6: 0 | Q6: 0 | R6: 0 | S6: 0 | T6: 0 | U6: =SUM(M6:N6,P6:S6) -> 0 | V6: =U6-S6 -> 0 | W6: 0 | X6: =X5+O6 -> 0
A7: 46301 | B7: 0 | C7: 0 | D7: 0 | E7: =SUM(B7:D7) -> 0 | F7: 0 | G7: 0 | H7: 0 | I7: =SUM(F7:H7) -> 0 | J7: =B7-F7 -> 0 | K7: =C7-G7 -> 0 | L7: =E7-I7 -> 0 | M7: 0 | N7: 0 | O7: =L7-M7-N7 -> 0 | P7: 0 | Q7: 0 | R7: 0 | S7: 0 | T7: 0 | U7: =SUM(M7:N7,P7:S7) -> 0 | V7: =U7-S7 -> 0 | W7: 0 | X7: =X6+O7 -> 0
A8: 46302 | B8: 0 | C8: 0 | D8: 0 | E8: =SUM(B8:D8) -> 0 | F8: 0 | G8: 0 | H8: 0 | I8: =SUM(F8:H8) -> 0 | J8: =B8-F8 -> 0 | K8: =C8-G8 -> 0 | L8: =E8-I8 -> 0 | M8: 0 | N8: 0 | O8: =L8-M8-N8 -> 0 | P8: 0 | Q8: 0 | R8: 0 | S8: 0 | T8: 0 | U8: =SUM(M8:N8,P8:S8) -> 0 | V8: =U8-S8 -> 0 | W8: 0 | X8: =X7+O8 -> 0
A9: 46303 | B9: 0 | C9: 0 | D9: 0 | E9: =SUM(B9:D9) -> 0 | F9: 0 | G9: 0 | H9: 0 | I9: =SUM(F9:H9) -> 0 | J9: =B9-F9 -> 0 | K9: =C9-G9 -> 0 | L9: =E9-I9 -> 0 | M9: 0 | N9: 0 | O9: =L9-M9-N9 -> 0 | P9: 0 | Q9: 0 | R9: 0 | S9: 0 | T9: 0 | U9: =SUM(M9:N9,P9:S9) -> 0 | V9: =U9-S9 -> 0 | W9: 0 | X9: =X8+O9 -> 0
A10: 46304 | B10: 0 | C10: 293.3 | D10: 0 | E10: =SUM(B10:D10) -> 293.3 | F10: 0 | G10: 127.65 | H10: 0 | I10: =SUM(F10:H10) -> 127.65 | J10: =B10-F10 -> 0 | K10: =C10-G10 -> 165.65 | L10: =E10-I10 -> 165.65 | M10: 0 | N10: 0 | O10: =L10-M10-N10 -> 165.65 | P10: 0 | Q10: 0 | R10: 0 | S10: 0 | T10: 0 | U10: =SUM(M10:N10,P10:S10) -> 0 | V10: =U10-S10 -> 0 | W10: 0 | X10: =X9+O10 -> 165.65
A11: 46305 | B11: 0 | C11: 2639.25 | D11: 0 | E11: =SUM(B11:D11) -> 2639.25 | F11: 0 | G11: 1148.85 | H11: 0 | I11: =SUM(F11:H11) -> 1148.85 | J11: =B11-F11 -> 0 | K11: =C11-G11 -> 1490.4 | L11: =E11-I11 -> 1490.4 | M11: 0 | N11: 0 | O11: =L11-M11-N11 -> 1490.4 | P11: 0 | Q11: 0 | R11: 0 | S11: 0 | T11: 0 | U11: =SUM(M11:N11,P11:S11) -> 0 | V11: =U11-S11 -> 0 | W11: 0 | X11: =X10+O11 -> 1656.05
A12: 46306 | B12: 0 | C12: 0 | D12: 0 | E12: =SUM(B12:D12) -> 0 | F12: 0 | G12: 0 | H12: 0 | I12: =SUM(F12:H12) -> 0 | J12: =B12-F12 -> 0 | K12: =C12-G12 -> 0 | L12: =E12-I12 -> 0 | M12: 0 | N12: 0 | O12: =L12-M12-N12 -> 0 | P12: 0 | Q12: 0 | R12: 0 | S12: 0 | T12: 0 | U12: =SUM(M12:N12,P12:S12) -> 0 | V12: =U12-S12 -> 0 | W12: 0 | X12: =X11+O12 -> 1656.05
A13: 46307 | B13: 0 | C13: 0 | D13: 0 | E13: =SUM(B13:D13) -> 0 | F13: 0 | G13: 0 | H13: 0 | I13: =SUM(F13:H13) -> 0 | J13: =B13-F13 -> 0 | K13: =C13-G13 -> 0 | L13: =E13-I13 -> 0 | M13: 0 | N13: 0 | O13: =L13-M13-N13 -> 0 | P13: 4000 | Q13: 0 | R13: 0 | S13: 0 | T13: 0 | U13: =SUM(M13:N13,P13:S13) -> 4000 | V13: =U13-S13 -> 4000 | W13: 0 | X13: =X12+O13 -> 1656.05
A14: 46308 | B14: 0 | C14: 120 | D14: 0 | E14: =SUM(B14:D14) -> 120 | F14: 0 | G14: 90 | H14: 0 | I14: =SUM(F14:H14) -> 90 | J14: =B14-F14 -> 0 | K14: =C14-G14 -> 30 | L14: =E14-I14 -> 30 | M14: 20 | N14: 800 | O14: =L14-M14-N14 -> -790 | P14: 1900 | Q14: 0 | R14: 0 | S14: 0 | T14: 0 | U14: =SUM(M14:N14,P14:S14) -> 2720 | V14: =U14-S14 -> 2720 | W14: 20 | X14: =X13+O14 -> 866.05
... A17: 46311 | B17: 0 | C17: 13140.1 | D17: 0 | E17: =SUM(B17:D17) -> 13140.1 | F17: 0 | G17: 10162.05 | H17: 0 | I17: =SUM(F17:H17) -> 10162.05 | J17: =B17-F17 -> 0 | K17: =C17-G17 -> 2978.05 | L17: =E17-I17 -> 2978.05 | M17: 0 | N17: 0 | O17: =L17-M17-N17 -> 2978.05 | P17: 0 | Q17: 0 | R17: 0 | S17: 0 | T17: 0 | U17: =SUM(M17:N17,P17:S17) -> 0 | V17: =U17-S17 -> 0 | W17: 0 | X17: =X16+O17 -> 6672.15

Sheet Ventas
A1: Fecha | B1: Usuario | C1: Documento | D1: Tipo | E1: Producto | F1: Cantidad | G1: Precio unitario | H1: Descuento registrado | I1: Venta neta | J1: Costo | K1: Utilidad bruta | L1: Origen del costo
A2: 46304 | B2: admin | C2: B012-1 | D2: Mercadería | E2: CAMARA DOMO 1MP HDCVI CAMERA HD HAC-T1A11N | F2: 1 | G2: 293.3 | H2: 0 | I2: 293.3 | J2: 127.65 | K2: 165.65 | L2: Costo de la venta
A3: 46305 | B3: admin | C3: B012-2 | D3: Mercadería | E3: CAMARA DOMO 1MP HDCVI CAMERA HD HAC-T1A11N | F3: 9 | G3: 293.25 | H3: 0 | I3: 2639.25 | J3: 1148.85 | K3: 1490.4 | L3: Costo de la venta
A4: 46308 | B4: superadmin | C4: B012-3 | D4: Mercadería | E4: CAMARA DOMO 1MP HDCVI CAMERA HD HAC-T1A11N | F4: 1 | G4: 120 | H4: 0 | I4: 120 | J4: 90 | K4: 30 | L4: Costo de la venta
A5: 46309 | B5: admin | C5: B012-4 | D5: Mercadería | E5: CAMARA DOMO 1MP HDCVI CAMERA HD HAC-T1A11N | F5: 1 | G5: 120 | H5: 0 | I5: 120 | J5: 90 | K5: 30 | L5: Costo de la venta
A6: 46309 | B6: admin | C6: B012-5 | D6: Mercadería | E6: HP LAPTOP 15-FD2378LA INTEL U7-255U 24GB 512GB FREEDOS | F6: 1 | G6: 12420.1 | H6: 0 | I6: 12420.1 | J6: 9622.05 | K6: 2798.05 | L6: Costo de la venta
A7: 46311 | B7: admin | C7: B012-6 | D7: Mercadería | E7: CAMARA DOMO 1MP HDCVI CAMERA HD HAC-T1A11N | F7: 1 | G7: 120 | H7: 0 | I7: 120 | J7: 90 | K7: 30 | L7: Costo de la venta
A8: 46311 | B8: admin | C8: B012-7 | D8: Mercadería | E8: CAMARA DOMO 1MP HDCVI CAMERA HD HAC-T1A11N | F8: 1 | G8: 120 | H8: 0 | I8: 120 | J8: 90 | K8: 30 | L8: Costo de la venta
A9: 46311 | B9: admin | C9: B012-8 | D9: Mercadería | E9: CAMARA DOMO 1MP HDCVI CAMERA HD HAC-T1A11N | F9: 1 | G9: 120 | H9: 0 | I9: 120 | J9: 90 | K9: 30 | L9: Costo de la venta
A10: 46311 | B10: admin | C10: B012-9 | D10: Mercadería | E10: CAMARA DOMO 1MP HDCVI CAMERA HD HAC-T1A11N | F10: 1 | G10: 120 | H10: 0 | I10: 120 | J10: 90 | K10: 30 | L10: Costo de la venta
A11: 46311 | B11: admin | C11: B012-10 | D11: Mercadería | E11: CAMARA DOMO 1MP HDCVI CAMERA HD HAC-T1A11N | F11: 1 | G11: 120 | H11: 0 | I11: 120 | J11: 90 | K11: 30 | L11: Costo de la venta
A12: 46311 | B12: admin | C12: B012-11 | D12: Mercadería | E12: HP LAPTOP 15-FD2378LA INTEL U7-255U 24GB 512GB FREEDOS | F12: 1 | G12: 12420.1 | H12: 0 | I12: 12420.1 | J12: 9622.05 | K12: 2798.05 | L12: Costo de la venta
A13: 46311 | B13: admin | C13: B012-12 | D13: Mercadería | E13: CAMARA DOMO 1MP HDCVI CAMERA HD HAC-T1A11N | F13: 1 | G13: 120 | H13: 0 | I13: 120 | J13: 90 | K13: 30 | L13: Costo de la venta

Sheet Caja y bancos
A1: ID | B1: Fecha | C1: Usuario | D1: Cuenta | E1: Operación registrada | F1: Concepto | G1: Proveedor | H1: Clasificación gerencial | I1: Importe (S/)
A2: 1 | B2: 46307 | C2: superadmin | D2: Banco BCP | E2: ENTREGA DE DINERO O DEPOSITO A BANCOS BCP-BBVA-NACION | F2: compra camaras | G2: DIGICORP | H2: proveedor | I2: 1000
A3: 2 | B3: 46307 | C3: superadmin | D3: Banco BCP | E3: ENTREGA DE DINERO O DEPOSITO A BANCOS BCP-BBVA-NACION | F3: compra de camaras op 23456 | G3: DIGICORP | H3: proveedor | I3: 3000
A4: 3 | B4: 46308 | C4: superadmin | D4: Bancos Varios | E4: ENTREGA DE DINERO O DEPOSITO A BANCOS BCP-BBVA-NACION | F4: compra de computadoras deltron | G4: ANS & J.V. S.A.C. | H4: proveedor | I4: 1900
A5: 4 | B5: 46308 | C5: superadmin | D5: Caja Principal | E5: VALE DE EGRESO | F5: Gasto Proyecto PROYECTO 310 - adelanto | H5: gasto | I5: 20
A6: 5 | B6: 46308 | C6: superadmin | D6: Caja Principal | E6: PAGO DE CLIENTE | F6: Adelanto Proyecto PROYECTO 308 - adelanto de impresora | H6: ingreso | I6: 20
A7: 6 | B7: 46308 | C7: superadmin | D7: Caja Principal | E7: PAGO A PERSONAL | F7: PLANILLA ADELANTO - FIORELA DEL PILAR ALARCON RAMIREZ / 2026-10 / 543678 | H7: personal | I7: 500
A8: 7 | B8: 46308 | C8: superadmin | D8: Banco BCP | E8: PAGO A PERSONAL | F8: PLANILLA ADELANTO - FIORELA DEL PILAR ALARCON RAMIREZ / 2026-10 / 456346346 ADELANTO | H8: personal | I8: 300

Sheet Criterios
A2: CRITERIOS Y COBERTURA
A4: Consolidado de todos los usuarios y almacenes. Importes en soles según registros del sistema, sin ajuste adicional de IGV.
A5: Ventas válidas: factura, boleta y nota de venta. Notas de crédito restan venta y costo registrados. Se excluyen anulados, proformas y ofertas (código 99).
A6: Utilidad neta operativa estimada = utilidad bruta - gastos operativos - pagos de personal. No incluye impuestos a la renta, depreciaciones ni obligaciones no registradas.
A7: Pagos a proveedores se muestran como salidas; no se descuentan otra vez de la utilidad porque el costo vendido ya está incluido. Si un pago corresponde a un gasto, reclasifica su tipo como gasto operativo.
A8: Cobros Yape/Plin se muestran aparte: no son salidas, gastos ni ventas adicionales. Se reconoce también el registro automático antiguo YAPE/PLIN. Otros registros del antiguo tipo 7 requieren clasificación.
A9: Los registros automáticos Tarjeta/Transferencia de ventas no se consideran gasto. Los demás registros del tipo depósitos requieren clasificar su destino real; pueden ser compras, gastos o traslados.
A10: Otras salidas no operativas se muestran sin reducir utilidad. Revisa su clasificación. El detalle de caja contiene todos los registros no anulados del período.
A11: La proyección es el promedio diario del período multiplicado por los días elegidos, incluidos días sin actividad. No es una garantía ni un saldo bancario.
A12: Este reporte usa gastos y pagos registrados en Caja y Banco. Compras, planillas o deudas sin pago registrado no se convierten automáticamente en gastos del período.
A14: Regla general por tipo. Las excepciones por movimiento se muestran en Caja y bancos.
A15: Tipo de caja | B15: Clasificación aplicada | C15: Importe registrado
A16: PAGO A PROVEEDOR | B16: proveedor | C16: 0
A17: VALE DE EGRESO | B17: gasto | C17: 20
A18: ENTREGA DE DINERO O DEPOSITO A BANCOS BCP-BBVA-NACION | B18: pendiente | C18: 5900
A19: PAGO A PERSONAL | B19: personal | C19: 800
A20: PAGOS ANTIGUOS (ANTES YAPE) | B20: pendiente | C20: 0
